json_cherry_pick/__init__.py
json_cherry_pick/mapper.so
json_cherry_pick/tests/__init__.py
json_cherry_pick/tests/test_json_cherry_pick.py
json_cherry_pick-0.3.22.dist-info/WHEEL
json_cherry_pick-0.3.22.dist-info/DESCRIPTION.rst
json_cherry_pick-0.3.22.dist-info/METADATA
json_cherry_pick-0.3.22.dist-info/RECORD
json_cherry_pick-0.3.22.dist-info/top_level.txt
json_cherry_pick-0.3.22.dist-info/metadata.json
